["[7,[[[1,\"1e+30011\",\"Seffy Roth\",null,20,800,83,1500,0,0,10,55,-7,0,[21,33,0,0,0,0],52,33,52,33,52,33,\"s\",null],[0,1,\"Onfroy\",\"GM\",31,350,73,1500,0,0,15,65,-6,5,[285,317,607,109,4983,0],68,45,68,45,68,45,\"m\",\"US\"]],1,726,-446,180,0,[1,0,4,7,8,2,0,1,7,2,2,2,0,7,1,1,1,1,6,1,7,5,1,8,3,6,1,2,2,3,1,8,6,1,0,4,1,1,1,3,4,5,7,3,2,4,7,4,2,1,1,5,1,6,6,5,2,5,1,1,1,1,5,7,1,1,1,1,1,1,0,2,0,3,6,7,1,8,3,1,0,1,2,2,1,4,2,0,1,5,1,8,6,1,1,2,1,6,2,8],0,270,1,0,0,1,0,20,0,0,[],[],0]]","[6,[1,1,800,83,0,760,0,[7],726,-446,235.18210755932432,76,[1,0,4,7,8,2,0,1,7,2,2,2,0,7,1,1,1,1,6,1,7,5,1,8,3,6,1,2,2,3,1,8,6,1,0,4,1,1,1,3,4,5,7,3,2,4,7,4,2,1,1,5,1,6,6,5,2,5,1,1,1,1,5,7,1,1,1,1,1,1,0,2,0,3,6,7,1,8,3,1,0,1,2,2,1,4,2,0,1,5,1,8,6,1,1,2,1,6,2,8],0,270,[{\"s\":[793,53,112,489,0,398,0,0],\"tele\":[],\"exp\":0,\"thor\":false,\"img\":0,\"time\":2230,\"change\":null,\"hole\":[372,63,62,44],\"damages\":[{\"n\":0,\"damage\":151.91695402640542,\"hp\":1349}],\"jumps\":[],\"show\":null,\"ss\":false,\"isStage\":true},{\"s\":[726,-446,235.18210755932432,999,0,0,2430,0],\"tele\":[],\"exp\":6,\"thor\":true,\"img\":0,\"time\":0,\"change\":null,\"hole\":[362,79,27,27],\"damages\":[{\"n\":0,\"damage\":0.13457537613795267,\"hp\":1349}],\"jumps\":[],\"show\":null,\"ss\":false}],100,[[4,770,179]],[[7,363,168]]]]","[6,[2,0,350,104,1,870,1,[],726,-446,415,76,[1,0,4,7,8,2,0,1,7,2,2,2,0,7,1,1,1,1,6,1,7,5,1,8,3,6,1,2,2,3,1,8,6,1,0,4,1,1,1,3,4,5,7,3,2,4,7,4,2,1,1,5,1,6,6,5,2,5,1,1,1,1,5,7,1,1,1,1,1,1,0,2,0,3,6,7,1,8,3,1,0,1,2,2,1,4,2,0,1,5,1,8,6,1,1,2,1,6,2,8],0,270,[{\"s\":[364,77,43,374,0,398,0,0],\"tele\":[0,678,47,678,47],\"exp\":7,\"thor\":false,\"img\":10,\"time\":1112,\"change\":null,\"hole\":[678,47,0,0],\"damages\":[],\"jumps\":[],\"show\":null,\"ss\":false},{\"s\":[],\"tele\":[],\"exp\":null,\"thor\":null,\"img\":null,\"time\":null,\"change\":null,\"hole\":[],\"damages\":[],\"wave\":[],\"orbit\":[],\"jumps\":[],\"is_lightning\":[],\"no_rotate\":null,\"camera\":null,\"show\":null,\"ss\":null}],0,[[7,866,195]],[[8,1204,143]]]]","[6,[3,1,800,83,0,760,0,[7],726,-446,458,76,[1,0,4,7,8,2,0,1,7,2,2,2,0,7,1,1,1,1,6,1,7,5,1,8,3,6,1,2,2,3,1,8,6,1,0,4,1,1,1,3,4,5,7,3,2,4,7,4,2,1,1,5,1,6,6,5,2,5,1,1,1,1,5,7,1,1,1,1,1,1,0,2,0,3,6,7,1,8,3,1,0,1,2,2,1,4,2,0,1,5,1,8,6,1,1,2,1,6,2,8],0,270,[{\"s\":[793,53,112,241,0,398,0,0],\"tele\":[],\"exp\":0,\"thor\":false,\"img\":0,\"time\":1000,\"change\":null,\"hole\":[700,35,62,44],\"damages\":[{\"n\":0,\"damage\":151.70162612375117,\"hp\":1198}],\"jumps\":[],\"show\":null,\"ss\":false},{\"s\":[],\"tele\":[],\"exp\":null,\"thor\":null,\"img\":null,\"time\":null,\"change\":null,\"hole\":[],\"damages\":[],\"wave\":[],\"orbit\":[],\"jumps\":[],\"is_lightning\":[],\"no_rotate\":null,\"camera\":null,\"show\":null,\"ss\":null}],200,[[8,302,137]],[[7,624,176]]]]","[6,[4,0,698,78,1,780,1,[7],726,-446,448,76,[1,0,4,7,8,2,0,1,7,2,2,2,0,7,1,1,1,1,6,1,7,5,1,8,3,6,1,2,2,3,1,8,6,1,0,4,1,1,1,3,4,5,7,3,2,4,7,4,2,1,1,5,1,6,6,5,2,5,1,1,1,1,5,7,1,1,1,1,1,1,0,2,0,3,6,7,1,8,3,1,0,1,2,2,1,4,2,0,1,5,1,8,6,1,1,2,1,6,2,8],0,270,[{\"s\":[709,50,50,147,0,387,0,16],\"tele\":[],\"exp\":8,\"thor\":false,\"img\":16,\"time\":700,\"change\":null,\"hole\":[778,70,59,40],\"damages\":[{\"n\":1,\"damage\":325.22306766081937,\"hp\":1175}],\"jumps\":[],\"show\":null,\"ss\":false},{\"s\":[],\"tele\":[],\"exp\":null,\"thor\":null,\"img\":null,\"time\":null,\"change\":null,\"hole\":[],\"damages\":[],\"wave\":[],\"orbit\":[],\"jumps\":[],\"is_lightning\":[],\"no_rotate\":null,\"camera\":null,\"show\":null,\"ss\":null}],100,[[8,302,137]],[[7,624,176]]]]","[6,[5,1,800,107,0,760,0,[7],726,-446,456,76,[1,0,4,7,8,2,0,1,7,2,2,2,0,7,1,1,1,1,6,1,7,5,1,8,3,6,1,2,2,3,1,8,6,1,0,4,1,1,1,3,4,5,7,3,2,4,7,4,2,1,1,5,1,6,6,5,2,5,1,1,1,1,5,7,1,1,1,1,1,1,0,2,0,3,6,7,1,8,3,1,0,1,2,2,1,4,2,0,1,5,1,8,6,1,1,2,1,6,2,8],0,270,[{\"s\":[785,80,127,170,0,398,0,0],\"tele\":[],\"exp\":0,\"thor\":false,\"img\":0,\"time\":618,\"change\":null,\"hole\":[720,75,62,44],\"damages\":[{\"n\":0,\"damage\":152.89819834441275,\"hp\":1046}],\"jumps\":[],\"show\":null,\"ss\":false},{\"s\":[],\"tele\":[],\"exp\":null,\"thor\":null,\"img\":null,\"time\":null,\"change\":null,\"hole\":[],\"damages\":[],\"wave\":[],\"orbit\":[],\"jumps\":[],\"is_lightning\":[],\"no_rotate\":null,\"camera\":null,\"show\":null,\"ss\":null}],300,[[8,302,137]],[[7,624,176]]]]","[6,[6,0,743,115,1,780,1,[7],726,-446,279.25102957207764,254,[1,0,4,7,8,2,0,1,7,2,2,2,0,7,1,1,1,1,6,1,7,5,1,8,3,6,1,2,2,3,1,8,6,1,0,4,1,1,1,3,4,5,7,3,2,4,7,4,2,1,1,5,1,6,6,5,2,5,1,1,1,1,5,7,1,1,1,1,1,1,0,2,0,3,6,7,1,8,3,1,0,1,2,2,1,4,2,0,1,5,1,8,6,1,1,2,1,6,2,8],0,438,[{\"s\":[749,85,58,168,0,387,0,16],\"tele\":[],\"exp\":8,\"thor\":false,\"img\":16,\"time\":686,\"change\":null,\"hole\":[812,82,59,40],\"damages\":[{\"n\":1,\"damage\":324.13457537613795,\"hp\":851}],\"jumps\":[],\"show\":null,\"ss\":false,\"isStage\":true},{\"s\":[726,-446,279.25102957207764,999,0,0,886,0],\"tele\":[],\"exp\":6,\"thor\":true,\"img\":0,\"time\":0,\"change\":null,\"hole\":[815,97,25,25],\"damages\":[{\"n\":1,\"damage\":31.849028301915094,\"hp\":820}],\"jumps\":[],\"show\":null,\"ss\":false},{\"s\":[],\"tele\":[],\"exp\":null,\"thor\":null,\"img\":null,\"time\":null,\"change\":null,\"hole\":[],\"damages\":[],\"wave\":[],\"orbit\":[],\"jumps\":[],\"is_lightning\":[],\"no_rotate\":null,\"camera\":null,\"show\":null,\"ss\":null}],200,[[8,302,201]],[[7,624,176]]]]","[6,[7,1,800,134,0,760,0,[7,9],726,-446,457,254,[1,0,4,7,8,2,0,1,7,2,2,2,0,7,1,1,1,1,6,1,7,5,1,8,3,6,1,2,2,3,1,8,6,1,0,4,1,1,1,3,4,5,7,3,2,4,7,4,2,1,1,5,1,6,6,5,2,5,1,1,1,1,5,7,1,1,1,1,1,1,0,2,0,3,6,7,1,8,3,1,0,1,2,2,1,4,2,0,1,5,1,8,6,1,1,2,1,6,2,8],0,438,[{\"s\":[790,92,117,105,0,398,0,0],\"tele\":[],\"exp\":0,\"thor\":false,\"img\":0,\"time\":510,\"change\":null,\"hole\":[765,98,62,44,765,98,62,44],\"damages\":[{\"n\":0,\"damage\":150.09856122554214,\"hp\":896},{\"n\":1,\"damage\":138.89521957873362,\"hp\":682}],\"jumps\":[],\"show\":null,\"ss\":false},{\"s\":[],\"tele\":[],\"exp\":null,\"thor\":null,\"img\":null,\"time\":null,\"change\":null,\"hole\":[],\"damages\":[],\"wave\":[],\"orbit\":[],\"jumps\":[],\"is_lightning\":[],\"no_rotate\":null,\"camera\":null,\"show\":null,\"ss\":null}],-100,[[7,1114,145]],[[7,1029,165]]]]","[6,[8,0,743,139,1,780,1,[],726,-446,453,254,[1,0,4,7,8,2,0,1,7,2,2,2,0,7,1,1,1,1,6,1,7,5,1,8,3,6,1,2,2,3,1,8,6,1,0,4,1,1,1,3,4,5,7,3,2,4,7,4,2,1,1,5,1,6,6,5,2,5,1,1,1,1,5,7,1,1,1,1,1,1,0,2,0,3,6,7,1,8,3,1,0,1,2,2,1,4,2,0,1,5,1,8,6,1,1,2,1,6,2,8],0,438,[{\"s\":[757,112,43,493,0,387,0,16],\"tele\":[],\"exp\":null,\"thor\":false,\"img\":16,\"time\":932,\"change\":null,\"hole\":[],\"damages\":[],\"jumps\":[],\"show\":null,\"ss\":false,\"isStage\":true},{\"s\":[1104,-32,137,493,0,387,932,16],\"tele\":[],\"exp\":8,\"thor\":false,\"img\":16,\"time\":2016,\"change\":null,\"hole\":[355,106,59,40],\"damages\":[],\"jumps\":[],\"show\":null,\"ss\":false},{\"s\":[],\"tele\":[],\"exp\":null,\"thor\":null,\"img\":null,\"time\":null,\"change\":null,\"hole\":[],\"damages\":[],\"wave\":[],\"orbit\":[],\"jumps\":[],\"is_lightning\":[],\"no_rotate\":null,\"camera\":null,\"show\":null,\"ss\":null}],200,[[7,1114,145]],[[7,1029,165]]]]","[6,[9,1,800,157,0,760,0,[7,9],726,-446,456,254,[1,0,4,7,8,2,0,1,7,2,2,2,0,7,1,1,1,1,6,1,7,5,1,8,3,6,1,2,2,3,1,8,6,1,0,4,1,1,1,3,4,5,7,3,2,4,7,4,2,1,1,5,1,6,6,5,2,5,1,1,1,1,5,7,1,1,1,1,1,1,0,2,0,3,6,7,1,8,3,1,0,1,2,2,1,4,2,0,1,5,1,8,6,1,1,2,1,6,2,8],0,438,[{\"s\":[782,109,133,65,0,398,0,0],\"tele\":[],\"exp\":0,\"thor\":false,\"img\":0,\"time\":372,\"change\":null,\"hole\":[765,121,62,44,765,121,62,44],\"damages\":[{\"n\":0,\"damage\":149.7873295964481,\"hp\":747},{\"n\":1,\"damage\":138.89521957873362,\"hp\":544}],\"jumps\":[],\"show\":null,\"ss\":false},{\"s\":[],\"tele\":[],\"exp\":null,\"thor\":null,\"img\":null,\"time\":null,\"change\":null,\"hole\":[],\"damages\":[],\"wave\":[],\"orbit\":[],\"jumps\":[],\"is_lightning\":[],\"no_rotate\":null,\"camera\":null,\"show\":null,\"ss\":null}],-500,[[7,1114,145]],[[7,1029,165]]]]","[6,[10,0,743,162,1,780,1,[7],726,-446,453,254,[1,0,4,7,8,2,0,1,7,2,2,2,0,7,1,1,1,1,6,1,7,5,1,8,3,6,1,2,2,3,1,8,6,1,0,4,1,1,1,3,4,5,7,3,2,4,7,4,2,1,1,5,1,6,6,5,2,5,1,1,1,1,5,7,1,1,1,1,1,1,0,2,0,3,6,7,1,8,3,1,0,1,2,2,1,4,2,0,1,5,1,8,6,1,1,2,1,6,2,8],0,438,[{\"s\":[757,135,43,159,0,387,0,16],\"tele\":[],\"exp\":8,\"thor\":false,\"img\":16,\"time\":506,\"change\":null,\"hole\":[818,132,59,40],\"damages\":[{\"n\":1,\"damage\":322.59707819925063,\"hp\":222}],\"jumps\":[],\"show\":null,\"ss\":false},{\"s\":[],\"tele\":[],\"exp\":null,\"thor\":null,\"img\":null,\"time\":null,\"change\":null,\"hole\":[],\"damages\":[],\"wave\":[],\"orbit\":[],\"jumps\":[],\"is_lightning\":[],\"no_rotate\":null,\"camera\":null,\"show\":null,\"ss\":null}],300,[[7,1114,145]],[[7,1029,165]]]]","[6,[11,1,800,170,0,940,0,[7],726,-446,456,254,[1,0,4,7,8,2,0,1,7,2,2,2,0,7,1,1,1,1,6,1,7,5,1,8,3,6,1,2,2,3,1,8,6,1,0,4,1,1,1,3,4,5,7,3,2,4,7,4,2,1,1,5,1,6,6,5,2,5,1,1,1,1,5,7,1,1,1,1,1,1,0,2,0,3,6,7,1,8,3,1,0,1,2,2,1,4,2,0,1,5,1,8,6,1,1,2,1,6,2,8],0,438,[{\"s\":[791,141,114,117,0,398,0,1],\"tele\":[],\"exp\":1,\"thor\":false,\"img\":1,\"time\":530,\"change\":null,\"hole\":[765,143,36,26],\"damages\":[{\"n\":0,\"damage\":139.46555814625137,\"hp\":608}],\"jumps\":[],\"show\":null,\"ss\":false},{\"s\":[791,141,114,117,0,398,0,1],\"tele\":[],\"exp\":1,\"thor\":false,\"img\":1,\"time\":530,\"change\":null,\"hole\":[765,143,36,26],\"damages\":[{\"n\":0,\"damage\":139.1339312526815,\"hp\":469}],\"jumps\":[],\"show\":null,\"ss\":false}],-400,[[7,1114,145]],[[7,1029,165]]]]","[13,{\"won\":0,\"getfornexgpintheparams\":1,\"npm\":1,\"scores\":[[0,1,\"Onfroy\",31,58,300,0,23,0],[1,\"1e+30011\",\"Seffy Roth\",20,0,0,1,0,0],[]],\"chat\":[]}]"]